ALU.v
module ALU (
    input  [31:0] a, b,
    input  [ 2:0] what_to_do ,
    output        branch_eval,
    output [31:0] y_out
);
    wire [31:0] add_out;
    assign add_out = a + b;

    wire [31:0] addi_out;
    assign addi_out = a + b;

    wire [31:0] sll_out;
    assign sll_out = a << b;

    wire [31:0] slt_out;
    assign slt_out = ($signed(a) < $signed(b) )? 1:0 ;

    wire [31:0] sw_out;
    assign sw_out = a + b;

    wire [31:0] lw_out;
    assign lw_out = a + b;

    
    assign y_out = (
        ((3'b000 == what_to_do) ? add_out :
            ((3'b001 == what_to_do) ? addi_out : 
                ((3'b010 == what_to_do) ? sll_out: 
                    ((3'b011 == what_to_do)? slt_out :
                        ((3'b100 == what_to_do) ? sw_out : 
                            (3'b101 == what_to_do)? lw_out:0
                        )
                    )
                )
            )
        )
    );
    
    assign branch_eval = (a==b)? 1'b1 : 1'b0;

endmodule

RISC_BUBBLE.v
//THIS IS THE REGISTER FILE WITH 32 registers
module RISC_BUBBLE (
	input         clk  ,
	//
	input  [ 4:0] addr1,
	input  [ 4:0] addr2,
	output [31:0] data1,
	output [31:0] data2,
	//
	input         write_enable   ,
	input  [ 4:0] addr3,
	input  [31:0] wdata
);

	reg [31:0] regmem[31:0];
	reg [31:0] data1       ;
	reg [31:0] data2       ;

	always @(addr1 or regmem[addr1]) begin
		if (0 == addr1) begin
			data1 = 0;
		end else begin
			data1 = regmem[addr1];
		end
	end

	always @(addr2 or regmem[addr2]) begin
		if (0 == addr2) begin
			data2 = 0;
		end else begin
			data2 = regmem[addr2];
		end
	end

	always@ (posedge clk) begin
		if(1'b1 == write_enable) begin
			regmem[addr3] = wdata;
		end
	end

endmodule

dataPath.v
`include "RISC_BUBBLE.v"
`include "ALU.v"
module dataPath (
	input         clk       ,
	input  [ 2:0] alucontrol,
	input         alu_src   ,
	input         branch    ,
	input         jump      ,
	input         mem_to_reg,
	input         mem_write ,
	input         reg_dst   ,
	input         reg_write ,
	// imem side
	input  [31:0] instr     ,
	output [31:0] pc        ,
	// dmem side
	input  [31:0] read_data ,
	output [31:0] alu_result,
	output [31:0] write_data
);

///////////////
	wire [31:0] pc_plus_4;
	assign pc_plus_4 = pc + 4;

	wire [31:0] pc_jump;
	assign pc_jump = {pc_plus_4[31:28], instr[25:0], 2'b00};

	wire branch_cond;
	wire pc_src;
	assign pc_src = branch & branch_cond;

	wire [31:0] pc_branch;
	assign pc_branch = pc_plus_4 + {extended_immediate[29:0], 2'b00};

	wire [31:0] pc_next;
	assign pc_next = jump ? pc_jump : (pc_src ? pc_branch : pc_plus_4);

	reg [31:0] pc;
	initial begin
		pc = 32'h00000000;
	end

	always @(posedge clk) begin
		pc = pc_next;
	end

/////////////////////

	wire [5:0] rt;
	assign rt = instr[20:16];

	wire [5:0] rd;
	assign rd = instr[15:11];

	wire [4:0] write_reg;
	assign write_reg = reg_dst ? rd : rt;

	wire [31:0] result;
	assign result = mem_to_reg ? read_data : alu_result ;

//connections to register file
	wire [31:0] reg_data1;
	wire [31:0] reg_data2;

	RISC_BUBBLE regfile (
		.clk  (clk         ),
		.write_enable   (reg_write   ),
		.addr1(instr[25:21]),
		.addr2(instr[20:16]),
		.addr3(write_reg   ),
		.wdata(result      ),
		.data1(reg_data1   ),
		.data2(reg_data2   )
	);


//input to alu
	wire [31:0] src_a;
	wire [31:0] src_b;

	assign src_a = reg_data1;
	assign src_b = alu_src ? extended_immediate : reg_data2;

	wire branch_eval;
	wire [31:0] alu_out;
	ALU alu (
		.a(src_a     ),
		.b (src_b     ),
		.what_to_do (alucontrol),
		.branch_eval (branch_eval ),
		.y_out(alu_out   )
	);
	assign alu_result = alu_out;
	assign branch_cond = branch_eval;

//sign extension of immediate: 16b to 32b
	wire [31:0] extended_immediate;	
	assign extended_immediate = {{16{instr[15]}}, instr[15:0]};

	assign write_data = reg_data2;

endmodule

controller.v
module controller (
	input  [31:0] instr     ,
	// other side
	output        branch    ,
	output        jump      ,
	output        mem_to_reg,
	output        mem_write ,
	output        reg_dst   ,
	output        reg_write ,
	// alu side
	output [ 2:0] alucontrol,
	output        alu_src
);

	/////////////////
	wire [5:0] opcode;
	assign opcode = instr[31:26];
	
	wire cond_for_add = (opcode == 0 );
    wire cond_for_addi = (opcode == 1);
    wire cond_for_sll = (opcode == 2);
    wire cond_for_slt = (opcode == 3);
    wire cond_for_sw = (opcode == 4);
    wire cond_for_lw = (opcode == 5);
    wire cond_for_beq = (opcode == 6);
    wire cond_for_j = (opcode == 7);

	wire cond_for_sub = (opcode == 8);
    wire cond_for_addu = (opcode == 9);
    wire cond_for_subu = (opcode == 10);
    wire cond_for_addiu = (opcode == 11);

    wire cond_for_and = (opcode == 12);
    wire cond_for_or = (opcode == 13);
    wire cond_for_andi = (opcode == 14);
    wire cond_for_ori = (opcode == 15);
    wire cond_for_bne = (opcode == 16);



	assign branch     = cond_for_beq;
	assign jump       = cond_for_j;
	assign mem_to_reg = cond_for_lw;
	assign mem_write  = cond_for_sw;
	assign reg_dst    = cond_for_add | cond_for_slt;
	assign reg_write  = cond_for_add | cond_for_sll| cond_for_slt | cond_for_addi | cond_for_lw;
	assign alu_src    = cond_for_addi | cond_for_sll| cond_for_lw | cond_for_sw;	

	reg [3:0] alu_command;
	always @(instr) begin
		casex (instr[31:26])
			6'b00000: alu_command = 3'b000;
			6'b00001: alu_command = 3'b001;
			6'b00010: alu_command = 3'b010;
			6'b00011: alu_command = 3'b011;
			6'b00100: alu_command = 3'b100;
			6'b00101: alu_command = 3'b101;
			6'b00110: alu_command = 3'b110;
			6'b00111: alu_command = 3'b111;
			default: alu_command = 3'b000;
		endcase
	end

	assign alucontrol = alu_command;

endmodule

manipulate.v
`include "controller.v"
`include "dataPath.v"
module manipulate (
    input         clk       ,

    // imem side
    input  [31:0] imem_data ,
    output [31:0] imem_addr ,

    // dmem side
    input  [31:0] dmem_rdata,
    output        dmem_we   ,
    output [31:0] dmem_addr ,
    output [31:0] dmem_wdata
);

    //control signals
    wire [2:0] alucontrol;
    wire       alu_src   ;
    wire       branch    ;
    wire       jump      ;
    wire       mem_to_reg;
    wire       reg_dst   ;
    wire       reg_write ;

    controller controller (
        .instr     (imem_data ),
        .alucontrol(alucontrol),
        .alu_src   (alu_src   ),
        .branch    (branch    ),
        .jump      (jump      ),
        .mem_to_reg(mem_to_reg),
        .mem_write (dmem_we   ),
        .reg_dst   (reg_dst   ),
        .reg_write (reg_write )
    );

    dataPath datapath (
        .clk       (clk       ),
        .alucontrol(alucontrol),
        .alu_src   (alu_src   ),
        .branch    (branch    ),
        .jump      (jump      ),
        .mem_to_reg(mem_to_reg),
        .mem_write (dmem_we   ),
        .reg_dst   (reg_dst   ),
        .reg_write (reg_write ),
        .instr     (imem_data ),
        .pc        (imem_addr ),
        .read_data (dmem_rdata),
        .alu_result(dmem_addr ),
        .write_data(dmem_wdata)
    );

endmodule

dataMemory.v
//VEDA LIKE READ + WRITE MEMORY
module dataMemory (
	input         clk  ,
	input         write_enable   ,
	input  [31:0] addr ,
	input  [31:0] wdata,
	output [31:0] rdata
);

	reg [31:0] memdata [1023:0];

	assign rdata = memdata[addr];

	always @(posedge clk) begin
		if(1'b1 == write_enable) begin
			memdata[addr] = wdata;
		end
	end

	initial begin
		memdata[0] = 32'h00000009; //N
		memdata[1] = 32'h00000008; //N-1
		memdata[2] = 32'd9;
		memdata[3] = -32'd56;
		memdata[4] = -32'd9;
		memdata[5] = 32'd17;
		memdata[6] = 32'd100;
		memdata[7] = 32'd2938;
		memdata[8] = -32'd1987;
		memdata[9] = 32'd2083;
		memdata[10] = 32'd1;
	end

endmodule

instrMemory.v
//READ ONLY VEDA MEMORY
module instrMemory (
	input clk,
	input  [ 5:0] addr,
	output [31:0] data
);

	reg [31:0] data;
	reg [31:0] memory [63:0];

	initial begin
		
			//jumps to bubbel sort execution, skipping the test instructions
			memory[0] = 32'b000111_000000_000000_000000_00001001; //j #04
		
			//test instructions: to check each instruction used in bubble sort
			memory[1] = 32'b000001_00000_00010_0000000000000101; //addi $2, $0, 5
			memory[2] = 32'b000001_00000_00011_0000000000000101; //addi $3, $0, 3
			memory[3] = 32'b000000_00010_00011_00100_00000_000000; //add $4, $2, $3
			memory[4] = 32'b000010_00100_00101_0000000000000010; //sll $5, $4, 2
			memory[5] = 32'b000011_00100_00101_00110_00000_000000; //slt $6, $5, $4
			memory[6] = 32'b000100_00000_00101_0000000000000000; //sw $5, (0)$zero
			memory[7] = 32'b000101_00000_00110_0000000000000000; //lw $6, (0)$zero
			memory[8] = 32'b000110_00010_00011_0000000000000001; //beq $2, $3, #04

			//bubble sort machine code
			memory[9] = 32'b000001_00000_00001_0000000000000000; //li $s0, 0
			memory[10] = 32'b000101_00000_00111_0000000000000001; //lw $s6, N-1;
			memory[11] = 32'b000101_00000_01110_0000000000000000; //lw $t4, N;
			memory[12]= 32'b000001_00000_01101_0000000000000000; //li $t3, 0;
			memory[13] = 32'b000001_00000_00010_0000000000000000; //li $s1, 0;
			memory[14] = 32'b000001_00000_01000_0000000000000010; //la $s7, numbers;
			memory[15] = 32'b000001_00010_10001_0000000000000000; //sll $t7, $s1, 0;
			memory[16] = 32'b000000_10001_01000_10001_00000_000000; //add $t7, $s7, $t7 
			memory[17] = 32'b000101_10001_01010_0000000000000000; //lw $t0, 0($t7)  
			memory[18] = 32'b000101_10001_01011_0000000000000001; //lw $t1, 4($t7)
			memory[19] = 32'b000011_01010_01011_01100_00000_000000; //slt $t2, $t0, $t1	
			memory[20] = 32'b000110_00000_01100_0000000000000001; //beq $t2, $zero, swap
			memory[21] = 32'b000111_000000_000000_000000_00011000; //j increment
			memory[22] = 32'b000100_10001_01011_0000000000000000; //sw $t1, 0($t7) 
			memory[23] = 32'b000100_10001_01010_0000000000000001; //sw $t0, 4($t7)
			memory[24] = 32'b000001_00010_00010_0000000000000001; //	addi $s1, $s1, 1				
			memory[25] = 32'b000000_00010_00001_00110_00000_000000; //add $s5, $s1, $s0 	
			memory[26] = 32'b000110_00111_00110_0000000000000001; //beq $s6, $s5, continue
			memory[27] = 32'b000111_000000_000000_000000_00001111; //j loop
			memory[28] = 32'b000001_00001_00001_0000000000000001; //addi $s0, $s0, 1
			memory[29] = 32'b000001_00000_00010_0000000000000000; //li $s1, 0
			memory[30] = 32'b000110_00001_00111_0000000000000001; //beq $s0, $s6, continue
			memory[31] = 32'b000111_000000_000000_000000_00001111; //j loop

			// memory[32] = 32'b000101_00000_01010_0000000000000000;
			// memory[33] = 32'b000101_00000_01010_0000000000000001;
			
			//data memory is now filled with the sorted array
			memory[32] = 32'b000101_00000_01010_0000000000000010;
			memory[33] = 32'b000101_00000_01010_0000000000000011;
			memory[34] = 32'b000101_00000_01010_0000000000000100;
			memory[35] = 32'b000101_00000_01010_0000000000000101;
			memory[36] = 32'b000101_00000_01010_0000000000000110;
			memory[37] = 32'b000101_00000_01010_0000000000000111;
			memory[38] = 32'b000101_00000_01010_0000000000001000;
			memory[39] = 32'b000101_00000_01010_0000000000001001;
			memory[40] = 32'b000101_00000_01010_0000000000001010;

			memory[41] = 32'h00000000;
			memory[42] = 32'h00000000;
			memory[43] = 32'h00000000;
			memory[44] = 32'h00000000;
			memory[45] = 32'h00000000;
			memory[46] = 32'h00000000;
			memory[47] = 32'h00000000;
			memory[48] = 32'h00000000;
			memory[49] = 32'h00000000;
			memory[50] = 32'h00000000;
			memory[51] = 32'h00000000;
			memory[52] = 32'h00000000;
			memory[53] = 32'h00000000;
			memory[54] = 32'h00000000;
			memory[55] = 32'h00000000;
			memory[56] = 32'h00000000;
			memory[57] = 32'h00000000;
			memory[58] = 32'h00000000;
			memory[59] = 32'h00000000;
			memory[60] = 32'h00000000;
			memory[61] = 32'h00000000;
			memory[62] = 32'h00000000;
			memory[63] = 32'h00000000;
	end

	always @(*) begin
		data = memory[addr];
	end

endmodule

CSE_BUBBLE.v
`include "instrMemory.v"
`include "dataMemory.v"
`include "manipulate.v"
module CSE_BUBBLE (
	input clk // clock
);

	wire [31:0] imem_data ; 
	wire [31:0] imem_addr ;
	
	wire [31:0] dmem_rdata;
	wire        dmem_we   ;
	wire [31:0] dmem_addr ;
	wire [31:0] dmem_wdata;

	//READ ONLY veda memory
	instrMemory imem (
		.clk(clk),
		.addr(imem_addr[7:2]),
		.data(imem_data     )
	);

	//READ + WRITE veda memory
	dataMemory dmem (
		.clk  (clk       ),
		.write_enable  (dmem_we   ),
		.addr (dmem_addr ),
		.wdata(dmem_wdata),
		.rdata(dmem_rdata)
	);

	manipulate man (
		.clk       (clk       ),
		.imem_data (imem_data ),
		.imem_addr (imem_addr ),
		.dmem_rdata(dmem_rdata),
		.dmem_we   (dmem_we   ),
		.dmem_addr (dmem_addr ),
		.dmem_wdata(dmem_wdata)
	);
	

endmodule

tb.v
`include "CSE_BUBBLE.v"
module tb;

    reg clock;
  
    CSE_BUBBLE uut (.clk(clock));

    // generate clock
    always begin
        #5 clock = ~clock;
    end

    initial begin
        $dumpfile("out.vcd");
        $dumpvars(0, uut);
    end

    initial begin
        clock = 0;
        #10000
        $finish;
    end

endmodule

out.vcd
$date
	Thu Apr 20 13:01:22 2023
$end
$version
	Icarus Verilog
$end
$timescale
	1s
$end
$scope module tb $end
$scope module uut $end
$var wire 1 ! clk $end
$var wire 32 " imem_data [31:0] $end
$var wire 32 # imem_addr [31:0] $end
$var wire 1 $ dmem_we $end
$var wire 32 % dmem_wdata [31:0] $end
$var wire 32 & dmem_rdata [31:0] $end
$var wire 32 ' dmem_addr [31:0] $end
$scope module dmem $end
$var wire 1 ! clk $end
$var wire 32 ( rdata [31:0] $end
$var wire 1 $ write_enable $end
$var wire 32 ) wdata [31:0] $end
$var wire 32 * addr [31:0] $end
$upscope $end
$scope module imem $end
$var wire 6 + addr [5:0] $end
$var wire 1 ! clk $end
$var reg 32 , data [31:0] $end
$upscope $end
$scope module man $end
$var wire 1 ! clk $end
$var wire 32 - dmem_rdata [31:0] $end
$var wire 32 . imem_data [31:0] $end
$var wire 1 / reg_write $end
$var wire 1 0 reg_dst $end
$var wire 1 1 mem_to_reg $end
$var wire 1 2 jump $end
$var wire 32 3 imem_addr [31:0] $end
$var wire 1 $ dmem_we $end
$var wire 32 4 dmem_wdata [31:0] $end
$var wire 32 5 dmem_addr [31:0] $end
$var wire 1 6 branch $end
$var wire 3 7 alucontrol [2:0] $end
$var wire 1 8 alu_src $end
$scope module controller $end
$var wire 1 8 alu_src $end
$var wire 1 6 branch $end
$var wire 32 9 instr [31:0] $end
$var wire 1 2 jump $end
$var wire 1 1 mem_to_reg $end
$var wire 1 $ mem_write $end
$var wire 1 0 reg_dst $end
$var wire 1 / reg_write $end
$var wire 6 : opcode [5:0] $end
$var wire 1 ; cond_for_sw $end
$var wire 1 < cond_for_subu $end
$var wire 1 = cond_for_sub $end
$var wire 1 > cond_for_slt $end
$var wire 1 ? cond_for_sll $end
$var wire 1 @ cond_for_ori $end
$var wire 1 A cond_for_or $end
$var wire 1 B cond_for_lw $end
$var wire 1 C cond_for_j $end
$var wire 1 D cond_for_bne $end
$var wire 1 E cond_for_beq $end
$var wire 1 F cond_for_andi $end
$var wire 1 G cond_for_and $end
$var wire 1 H cond_for_addu $end
$var wire 1 I cond_for_addiu $end
$var wire 1 J cond_for_addi $end
$var wire 1 K cond_for_add $end
$var wire 3 L alucontrol [2:0] $end
$var reg 4 M alu_command [3:0] $end
$upscope $end
$scope module datapath $end
$var wire 32 N alu_result [31:0] $end
$var wire 1 8 alu_src $end
$var wire 3 O alucontrol [2:0] $end
$var wire 1 6 branch $end
$var wire 1 P branch_cond $end
$var wire 1 ! clk $end
$var wire 32 Q instr [31:0] $end
$var wire 1 2 jump $end
$var wire 1 1 mem_to_reg $end
$var wire 1 $ mem_write $end
$var wire 1 R pc_src $end
$var wire 32 S read_data [31:0] $end
$var wire 1 0 reg_dst $end
$var wire 1 / reg_write $end
$var wire 32 T src_a [31:0] $end
$var wire 32 U write_data [31:0] $end
$var wire 5 V write_reg [4:0] $end
$var wire 32 W src_b [31:0] $end
$var wire 6 X rt [5:0] $end
$var wire 32 Y result [31:0] $end
$var wire 32 Z reg_data2 [31:0] $end
$var wire 32 [ reg_data1 [31:0] $end
$var wire 6 \ rd [5:0] $end
$var wire 32 ] pc_plus_4 [31:0] $end
$var wire 32 ^ pc_next [31:0] $end
$var wire 32 _ pc_jump [31:0] $end
$var wire 32 ` pc_branch [31:0] $end
$var wire 32 a extended_immediate [31:0] $end
$var wire 1 b branch_eval $end
$var wire 32 c alu_out [31:0] $end
$var reg 32 d pc [31:0] $end
$scope module alu $end
$var wire 32 e a [31:0] $end
$var wire 32 f b [31:0] $end
$var wire 3 g what_to_do [2:0] $end
$var wire 32 h y_out [31:0] $end
$var wire 32 i sw_out [31:0] $end
$var wire 32 j slt_out [31:0] $end
$var wire 32 k sll_out [31:0] $end
$var wire 32 l lw_out [31:0] $end
$var wire 1 b branch_eval $end
$var wire 32 m addi_out [31:0] $end
$var wire 32 n add_out [31:0] $end
$upscope $end
$scope module regfile $end
$var wire 5 o addr1 [4:0] $end
$var wire 5 p addr2 [4:0] $end
$var wire 5 q addr3 [4:0] $end
$var wire 1 ! clk $end
$var wire 32 r wdata [31:0] $end
$var wire 1 / write_enable $end
$var reg 32 s data1 [31:0] $end
$var reg 32 t data2 [31:0] $end
$upscope $end
$upscope $end
$upscope $end
$upscope $end
$upscope $end
$enddefinitions $end
$comment Show the parameter values. $end
$dumpall
$end
#0
$dumpvars
b0 t
b0 s
b0 r
b0 q
b0 p
b0 o
b0 n
b0 m
b0 l
b0 k
b0 j
b0 i
b0 h
b111 g
b0 f
b0 e
b0 d
b0 c
1b
b1001 a
b101000 `
b100100 _
b100100 ^
b100 ]
b0 \
b0 [
b0 Z
b0 Y
b0 X
b0 W
b0 V
b0 U
b0 T
b1001 S
0R
b11100000000000000000000001001 Q
1P
b111 O
b0 N
b111 M
b111 L
0K
0J
0I
0H
0G
0F
0E
0D
1C
0B
0A
0@
0?
0>
0=
0<
0;
b111 :
b11100000000000000000000001001 9
08
b111 7
06
b0 5
b0 4
b0 3
12
01
00
0/
b11100000000000000000000001001 .
b1001 -
b11100000000000000000000001001 ,
b0 +
b0 *
b0 )
b1001 (
b0 '
b1001 &
b0 %
0$
b0 #
b11100000000000000000000001001 "
0!
$end
#5
b0 Y
b0 r
b1001 &
b1001 (
b1001 -
b1001 S
b0 '
b0 *
b0 5
b0 N
b0 c
b0 h
18
b0 j
1P
1b
1/
b1 V
b1 q
b0 n
b0 m
b0 k
b0 i
b0 l
b0 W
b0 f
b1 7
b1 L
b1 O
b1 g
b101000 ^
bx %
bx )
bx 4
bx U
bx Z
bx t
b1 M
1J
02
0C
b1 :
b1000000000000000000 _
b1 X
b1 p
b0 a
b100000000010000000000000000 "
b100000000010000000000000000 ,
b100000000010000000000000000 .
b100000000010000000000000000 9
b100000000010000000000000000 Q
b1001 +
b101000 `
b101000 ]
b100100 #
b100100 3
b100100 d
1!
#10
0!
#15
b1000 &
b1000 (
b1000 -
b1000 S
b1 '
b1 *
b1 5
b1 N
b1 c
b1 h
b111 V
b111 q
b1 j
0P
0b
b101 7
b101 L
b101 O
b101 g
b1000 Y
b1000 r
b1 n
b1 m
b1 i
b1 l
b1 W
b1 f
b101 M
0J
11
1B
b101 :
b111000000000000000100 _
b111 X
b111 p
b1 a
b101100 ^
b10100000001110000000000000001 "
b10100000001110000000000000001 ,
b10100000001110000000000000001 .
b10100000001110000000000000001 9
b10100000001110000000000000001 Q
b1010 +
bx %
bx )
bx 4
bx U
bx Z
bx t
b110000 `
b101100 ]
b101000 #
b101000 3
b101000 d
1!
#20
0!
#25
b1001 Y
b1001 r
b1001 &
b1001 (
b1001 -
b1001 S
b0 '
b0 *
b0 5
b0 N
b0 c
b0 h
b1110 V
b1110 q
b0 j
1P
1b
b0 n
b0 m
b0 i
b0 l
b0 W
b0 f
b1110000000000000000000 _
b1110 X
b1110 p
b0 a
b110000 ^
b10100000011100000000000000000 "
b10100000011100000000000000000 ,
b10100000011100000000000000000 .
b10100000011100000000000000000 9
b10100000011100000000000000000 Q
bx %
bx )
bx 4
bx U
bx Z
bx t
b1011 +
b110000 `
b110000 ]
b101100 #
b101100 3
b101100 d
1!
#30
0!
#35
b1001 &
b1001 (
b1001 -
b1001 S
b0 '
b0 *
b0 5
b0 N
b0 c
b0 h
b0 j
1P
1b
b0 n
b0 m
b0 k
b0 i
b0 l
b0 W
b0 f
18
b1101 V
b1101 q
b1 7
b1 L
b1 O
b1 g
1/
b0 Y
b0 r
b1 M
1J
01
0B
b1 :
b1101000000000000000000 _
b1101 X
b1101 p
b110100 ^
b100000011010000000000000000 "
b100000011010000000000000000 ,
b100000011010000000000000000 .
b100000011010000000000000000 9
b100000011010000000000000000 Q
b1100 +
bx %
bx )
bx 4
bx U
bx Z
bx t
b110100 `
b110100 ]
b110000 #
b110000 3
b110000 d
1!
#40
0!
#45
b10 V
b10 q
b10000000000000000000 _
b10 X
b10 p
b111000 ^
b100000000100000000000000000 "
b100000000100000000000000000 ,
b100000000100000000000000000 .
b100000000100000000000000000 9
b100000000100000000000000000 Q
bx %
bx )
bx 4
bx U
bx Z
bx t
b1101 +
b111000 `
b111000 ]
b110100 #
b110100 3
b110100 d
1!
#50
0!
#55
b10 Y
b10 r
b10 '
b10 *
b10 5
b10 N
b10 c
b10 h
b1000 V
b1000 q
b1 j
0P
0b
b10 n
b10 m
b10 i
b10 l
b10 W
b10 f
b1000000000000000001000 _
b1000 X
b1000 p
b10 a
b111100 ^
b100000010000000000000000010 "
b100000010000000000000000010 ,
b100000010000000000000000010 .
b100000010000000000000000010 9
b100000010000000000000000010 Q
b1110 +
bx %
bx )
bx 4
bx U
bx Z
bx t
b1000100 `
b111100 ]
b111000 #
b111000 3
b111000 d
1!
#60
0!
#65
b0 Y
b0 r
b0 '
b0 *
b0 5
b0 N
b0 c
b0 h
b10001 V
b10001 q
b0 j
1P
1b
b0 n
b0 m
b0 i
b0 l
b0 W
b0 f
b1010001000000000000000000 _
b10001 X
b10 o
b10001 p
b0 a
b1000000 ^
b100010100010000000000000000 "
b100010100010000000000000000 ,
b100010100010000000000000000 .
b100010100010000000000000000 9
b100010100010000000000000000 Q
bx %
bx )
bx 4
bx U
bx Z
bx t
b1111 +
b1000000 `
b1000000 ]
b111100 #
b111100 3
b111100 d
1!
#70
0!
#75
b1 j
b10 Y
b10 r
08
b1001 &
b1001 (
b1001 -
b1001 S
b10 '
b10 *
b10 5
b10 N
b10 c
b10 h
1/
b10001 V
b10001 q
0P
0b
b0 7
b0 L
b0 O
b0 g
10
b10 n
b10 m
b10 i
b10 l
b10 W
b10 f
b0 M
1K
0J
b0 :
b1000101000100010000000000000 _
b1000 X
b10001 \
b10001 o
b1000 p
b11111111111111111000100000000000 a
b1000100 ^
b10001010001000100000000000 "
b10001010001000100000000000 ,
b10001010001000100000000000 .
b10001010001000100000000000 9
b10001010001000100000000000 Q
b10000 +
b10 %
b10 )
b10 4
b10 U
b10 Z
b10 t
b11111111111111100010000001000100 `
b1000100 ]
b1000000 #
b1000000 3
b1000000 d
1!
#80
0!
#85
18
b1010 V
b1010 q
b0 W
b0 f
b101 7
b101 L
b101 O
b101 g
00
bx %
bx )
bx 4
bx U
bx Z
bx t
b1001 Y
b1001 r
b101 M
0K
11
1B
b101 :
b1000101010000000000000000000 _
b1010 X
b0 \
b1010 p
b0 a
b1001 &
b1001 (
b1001 -
b1001 S
b10 '
b10 *
b10 5
b10 N
b10 c
b10 h
b0 j
0P
0b
b1001000 ^
b10110001010100000000000000000 "
b10110001010100000000000000000 ,
b10110001010100000000000000000 .
b10110001010100000000000000000 9
b10110001010100000000000000000 Q
b10 n
b10 m
b10 k
b10 i
b10 l
b10 T
b10 e
b10 [
b10 s
b10001 +
b1001000 `
b1001000 ]
b1000100 #
b1000100 3
b1000100 d
1!
#90
0!
#95
b11111111111111111111111111001000 Y
b11111111111111111111111111001000 r
b11111111111111111111111111001000 &
b11111111111111111111111111001000 (
b11111111111111111111111111001000 -
b11111111111111111111111111001000 S
b11 '
b11 *
b11 5
b11 N
b11 c
b11 h
b1011 V
b1011 q
b11 n
b11 m
b100 k
b11 i
b11 l
b1 W
b1 f
b1000101011000000000000000100 _
b1011 X
b1011 p
b1 a
b1001100 ^
b10110001010110000000000000001 "
b10110001010110000000000000001 ,
b10110001010110000000000000001 .
b10110001010110000000000000001 9
b10110001010110000000000000001 Q
b10010 +
bx %
bx )
bx 4
bx U
bx Z
bx t
b1010000 `
b1001100 ]
b1001000 #
b1001000 3
b1001000 d
1!
#100
0!
#105
b1001 &
b1001 (
b1001 -
b1001 S
b0 '
b0 *
b0 5
b0 N
b0 c
b0 h
b1100 V
b1100 q
08
b0 j
b11 7
b11 L
b11 O
b11 g
10
1/
b0 Y
b0 r
b1001 T
b1001 e
b1001 [
b1001 s
b11111111111111111111111111010001 n
b11111111111111111111111111010001 m
b0 k
b11111111111111111111111111010001 i
b11111111111111111111111111010001 l
b11111111111111111111111111001000 W
b11111111111111111111111111001000 f
b11 M
1>
01
0B
b11 :
b101001011011000000000000000 _
b1100 \
b1010 o
b110000000000000 a
b1010000 ^
b1101010010110110000000000000 "
b1101010010110110000000000000 ,
b1101010010110110000000000000 .
b1101010010110110000000000000 9
b1101010010110110000000000000 Q
b11111111111111111111111111001000 %
b11111111111111111111111111001000 )
b11111111111111111111111111001000 4
b11111111111111111111111111001000 U
b11111111111111111111111111001000 Z
b11111111111111111111111111001000 t
b10011 +
b11000000001010000 `
b1010000 ]
b1001100 #
b1001100 3
b1001100 d
1!
#110
0!
#115
1R
0/
1P
1b
b1100 V
b1100 q
b0 W
b0 f
b110 7
b110 L
b110 O
b110 g
00
b0 n
b0 m
b0 i
b0 l
b0 T
b0 e
b0 [
b0 s
b0 %
b0 )
b0 4
b0 U
b0 Z
b0 t
b110 M
0>
16
1E
b110 :
b1100000000000000000100 _
b1100 X
b0 \
b0 o
b1100 p
b1 a
b1011000 ^
b11000000011000000000000000001 "
b11000000011000000000000000001 ,
b11000000011000000000000000001 .
b11000000011000000000000000001 9
b11000000011000000000000000001 Q
b10100 +
b1011000 `
b1010100 ]
b1010000 #
b1010000 3
b1010000 d
1!
#120
0!
#125
b10 Y
b10 r
b10 '
b10 *
b10 5
b10 N
b10 c
b10 h
b1011 V
b1011 q
0P
0b
b100 7
b100 L
b100 O
b100 g
18
0R
b10 n
b10 m
b10 k
b10 i
b10 l
b10 T
b10 e
b10 [
b10 s
b11111111111111111111111111001000 %
b11111111111111111111111111001000 )
b11111111111111111111111111001000 4
b11111111111111111111111111001000 U
b11111111111111111111111111001000 Z
b11111111111111111111111111001000 t
b100 M
1$
1;
06
0E
b100 :
b1000101011000000000000000000 _
b1011 X
b10001 o
b1011 p
b0 a
b1011100 ^
b10010001010110000000000000000 "
b10010001010110000000000000000 ,
b10010001010110000000000000000 .
b10010001010110000000000000000 9
b10010001010110000000000000000 Q
b10110 +
b1011100 `
b1011100 ]
b1011000 #
b1011000 3
b1011000 d
1!
#130
0!
#135
b11 Y
b11 r
b11 '
b11 *
b11 5
b11 N
b11 c
b11 h
b1010 V
b1010 q
b1001 %
b1001 )
b1001 4
b1001 U
b1001 Z
b1001 t
b11 n
b11 m
b100 k
b11 i
b11 l
b1 W
b1 f
b1000101010000000000000000100 _
b1010 X
b1010 p
b1 a
b1100000 ^
b10010001010100000000000000001 "
b10010001010100000000000000001 ,
b10010001010100000000000000001 .
b10010001010100000000000000001 9
b10010001010100000000000000001 Q
b10111 +
b1100100 `
b1100000 ]
b1011100 #
b1011100 3
b1011100 d
b11111111111111111111111111001000 &
b11111111111111111111111111001000 (
b11111111111111111111111111001000 -
b11111111111111111111111111001000 S
1!
#140
0!
#145
b1 Y
b1 r
b1 '
b1 *
b1 5
b1 N
b1 c
b1 h
0P
0b
1/
b1 W
b1 f
b10 V
b10 q
b1 j
b1 7
b1 L
b1 O
b1 g
18
b1 n
b1 m
b0 k
b1 i
b1 l
b0 T
b0 e
b0 [
b0 s
b0 %
b0 )
b0 4
b0 U
b0 Z
b0 t
b1 M
1J
0$
0;
b1 :
b1000010000000000000000100 _
b10 X
b10 o
b10 p
b1100100 ^
b100010000100000000000000001 "
b100010000100000000000000001 ,
b100010000100000000000000001 .
b100010000100000000000000001 9
b100010000100000000000000001 Q
b11000 +
b1000 &
b1000 (
b1000 -
b1000 S
b1101000 `
b1100100 ]
b1100000 #
b1100000 3
b1100000 d
1!
#150
0!
#155
08
1/
b110 V
b110 q
b0 7
b0 L
b0 O
b0 g
10
b0 W
b0 f
b1 Y
b1 r
b0 M
1K
0J
b0 :
b1000001001100000000000000 _
b1 X
b110 \
b1 p
b11000000000000 a
b1000 &
b1000 (
b1000 -
b1000 S
b1 '
b1 *
b1 5
b1 N
b1 c
b1 h
b1101000 ^
b10000010011000000000000 "
b10000010011000000000000 ,
b10000010011000000000000 .
b10000010011000000000000 9
b10000010011000000000000 Q
b0 j
0P
0b
b11001 +
b1 n
b1 m
b1 k
b1 i
b1 l
b1 T
b1 e
b1 [
b1 s
b0 %
b0 )
b0 4
b0 U
b0 Z
b0 t
b1100000001101000 `
b1101000 ]
b1100100 #
b1100100 3
b1100100 d
1!
#160
0!
